README.md
setup.cfg
setup.py
thanosclient/__init__.py
thanosclient/client.py
thanosclient.egg-info/PKG-INFO
thanosclient.egg-info/SOURCES.txt
thanosclient.egg-info/dependency_links.txt
thanosclient.egg-info/requires.txt
thanosclient.egg-info/top_level.txt