Metadata-Version: 2.1
Name: thanosclient
Version: 1.0.9
Summary: cipher client
Home-page: UNKNOWN
Author: ams
License: UNKNOWN
Platform: UNKNOWN
